{
  "tconstruct:tools/materials_and_you": {
    "criteria": {
      "crafted_book": "2024-07-27 20:10:22 +0900"
    },
    "done": true
  },
  "minecraft:recipes/transportation/acacia_boat": {
    "criteria": {
      "in_water": "2024-07-27 20:15:05 +0900"
    },
    "done": true
  },
  "minecraft:recipes/transportation/oak_boat": {
    "criteria": {
      "in_water": "2024-07-27 20:15:05 +0900"
    },
    "done": true
  },
  "tconstruct:internal/starting_book": {
    "criteria": {
      "tick": "2024-07-27 20:10:22 +0900"
    },
    "done": true
  },
  "farmersdelight:main/root": {
    "criteria": {
      "seeds": "2024-07-27 20:10:22 +0900"
    },
    "done": true
  },
  "create:root": {
    "criteria": {
      "0": "2024-07-27 20:10:22 +0900"
    },
    "done": true
  },
  "minecraft:recipes/transportation/dark_oak_boat": {
    "criteria": {
      "in_water": "2024-07-27 20:15:05 +0900"
    },
    "done": true
  },
  "minecraft:recipes/transportation/birch_boat": {
    "criteria": {
      "in_water": "2024-07-27 20:15:05 +0900"
    },
    "done": true
  },
  "minecraft:recipes/transportation/jungle_boat": {
    "criteria": {
      "in_water": "2024-07-27 20:15:05 +0900"
    },
    "done": true
  },
  "minecraft:recipes/transportation/spruce_boat": {
    "criteria": {
      "in_water": "2024-07-27 20:15:05 +0900"
    },
    "done": true
  },
  "minecraft:adventure/adventuring_time": {
    "criteria": {
      "minecraft:river": "2024-07-27 20:15:09 +0900",
      "minecraft:stony_shore": "2024-07-27 20:13:44 +0900",
      "minecraft:forest": "2024-07-27 20:10:22 +0900"
    },
    "done": false
  },
  "DataVersion": 2975
}